easybits/__init__.py
easybits/errors.py
easybits/util.py
easybits-0.1.4.dist-info/METADATA
easybits-0.1.4.dist-info/WHEEL
easybits-0.1.4.dist-info/RECORD
