Metadata-Version: 2.3
Name: easybits
Version: 0.1.4
Summary: A friendly interface for exploring bits.
Author: Chris Proctor
Author-email: chris@chrisproctor.net
Requires-Python: >=3.9,<4.0
Classifier: Programming Language :: Python :: 3
Classifier: Programming Language :: Python :: 3.9
Classifier: Programming Language :: Python :: 3.10
Classifier: Programming Language :: Python :: 3.11
Classifier: Programming Language :: Python :: 3.12
Classifier: Programming Language :: Python :: 3.13
Requires-Dist: bitarray (>=3.0.0,<4.0.0)
